{
  "id": 11497,
  "title": "Haunted History Walking Tour",
  "slug": "haunted-history-walking-tour",
  "date": "2021-10-13T03:57:04",
  "author": "Staff",
  "category": [
    "Play"
  ],
  "tags": [
    "doylestown cardinal",
    "doylestown cemetary",
    "The Bucks County Civil War Museum"
  ],
  "excerpt": "<p>The Bucks County Civil War Museum will be hosting a Haunted History walking tour through Doylestown on Saturday, October 30th at 7:00pm. They will be meeting in the court yard of the Museum, located at 32 North Broad Street and Garden Alley. The tour will then take a stroll through the heart of town. It [&hellip;]</p>\n",
  "content": "<p class=\"p1\"><span class=\"s1\">T</span><span class=\"s2\">he Bucks County Civil War Museum will be hosting a Haunted History walking tour through Doylestown on Saturday, October 30th at 7:00pm. They will be meeting in the court yard of the Museum, located at 32 North Broad Street and Garden Alley. The tour will then take a stroll through the heart of town. It will conclude in the Doylestown Cemetery. Tickets are limited and are $10 a person or $30 per family, which includes a membership to the Bucks County Civil War RoundTable Museum and Library. To reserve tickets please contact them at <a href=\"mailto:allie.ann.smith@gmail.com\">allie.ann.smith@gmail.com</a><span class=\"Apple-converted-space\">  </span>or call (215) 822-1562</span></p>\n",
  "thumbnail": "https://doylestowncardinal.com/wp-content/uploads/2021/10/spook-louder.jpg"
}